dou.py
setup.py
dou.egg-info/PKG-INFO
dou.egg-info/SOURCES.txt
dou.egg-info/dependency_links.txt
dou.egg-info/top_level.txt