Metadata-Version: 1.0
Name: dou
Version: 0.0.1
Summary: dou egg
Home-page: http://liluo.org
Author: liluo
Author-email: i@liluo.org
License: MIT License
Keywords: dou
Platform: any
